smores/__init__.py
smores/__version__.py
smores/class_registry.py
smores/parser.py
smores/smores.py
smores/utils.py
smores-0.0.7.dist-info/DESCRIPTION.rst
smores-0.0.7.dist-info/METADATA
smores-0.0.7.dist-info/RECORD
smores-0.0.7.dist-info/WHEEL
smores-0.0.7.dist-info/metadata.json
smores-0.0.7.dist-info/top_level.txt
