Metadata-Version: 2.0
Name: smores
Version: 0.0.7
Summary: Allows you to create a schema for templates with a tag syntax easy enough for end users.
Home-page: https://github.com/codylandry/Smores
Author: Cody Landry
Author-email: cody.landry@me.com
License: MIT
Platform: UNKNOWN
Classifier: License :: OSI Approved :: MIT License
Classifier: Programming Language :: Python
Classifier: Programming Language :: Python :: 2.6
Classifier: Programming Language :: Python :: 2.7
Classifier: Programming Language :: Python :: 3
Classifier: Programming Language :: Python :: 3.3
Classifier: Programming Language :: Python :: 3.4
Classifier: Programming Language :: Python :: 3.5
Classifier: Programming Language :: Python :: 3.6
Classifier: Programming Language :: Python :: Implementation :: CPython
Classifier: Programming Language :: Python :: Implementation :: PyPy
Requires-Dist: marshmallow
Requires-Dist: Jinja2
Requires-Dist: pyparsing
Provides-Extra: docs
Requires-Dist: pydocmd; extra == 'docs'
Requires-Dist: mkdocs; extra == 'docs'
Requires-Dist: recommonmark; extra == 'docs'
Provides-Extra: test
Requires-Dist: pytest; extra == 'test'
Requires-Dist: pony; extra == 'test'
Requires-Dist: pytest-runner; extra == 'test'
Requires-Dist: coveralls; extra == 'test'
Requires-Dist: coverage; extra == 'test'
Provides-Extra: utils
Requires-Dist: bs4; extra == 'utils'
